LICENSE
MANIFEST.in
README.rst
setup.py
yaurtww/__about__.py
yaurtww/__init__.py
yaurtww/manifest.py
yaurtww.egg-info/PKG-INFO
yaurtww.egg-info/SOURCES.txt
yaurtww.egg-info/dependency_links.txt
yaurtww.egg-info/entry_points.txt
yaurtww.egg-info/requires.txt
yaurtww.egg-info/top_level.txt