Metadata-Version: 1.1
Name: yaurtww
Version: 0.0.1
Summary: Yet Another Urban Terror Wget Wrapper.
Home-page: https://github.com/urtdevs/yaurtww
Author: Jon Chen
Author-email: bsd@voltaire.sh
License: BSD 3-Clause
Platform: UNKNOWN
Classifier: Intended Audience :: Developers
Classifier: License :: OSI Approved :: BSD License
Classifier: Natural Language :: English
Classifier: Operating System :: MacOS :: MacOS X
Classifier: Operating System :: POSIX
Classifier: Operating System :: POSIX :: BSD
Classifier: Operating System :: POSIX :: Linux
Classifier: Programming Language :: Python
Classifier: Programming Language :: Python :: 2
Classifier: Programming Language :: Python :: 2.7
Classifier: Programming Language :: Python :: Implementation :: CPython
Classifier: Topic :: Games/Entertainment :: First Person Shooters
